pyhugegraph/__init__.py
pyhugegraph/client.py
pyhugegraph/api/__init__.py
pyhugegraph/api/auth.py
pyhugegraph/api/common.py
pyhugegraph/api/graph.py
pyhugegraph/api/graphs.py
pyhugegraph/api/gremlin.py
pyhugegraph/api/metric.py
pyhugegraph/api/rank.py
pyhugegraph/api/rebuild.py
pyhugegraph/api/schema.py
pyhugegraph/api/services.py
pyhugegraph/api/task.py
pyhugegraph/api/traverser.py
pyhugegraph/api/variable.py
pyhugegraph/api/version.py
pyhugegraph/api/schema_manage/__init__.py
pyhugegraph/api/schema_manage/edge_label.py
pyhugegraph/api/schema_manage/index_label.py
pyhugegraph/api/schema_manage/property_key.py
pyhugegraph/api/schema_manage/vertex_label.py
pyhugegraph/example/__init__.py
pyhugegraph/example/hugegraph_example.py
pyhugegraph/example/hugegraph_test.py
pyhugegraph/structure/__init__.py
pyhugegraph/structure/edge_data.py
pyhugegraph/structure/edge_label_data.py
pyhugegraph/structure/gremlin_data.py
pyhugegraph/structure/index_label_data.py
pyhugegraph/structure/property_key_data.py
pyhugegraph/structure/rank_data.py
pyhugegraph/structure/response_data.py
pyhugegraph/structure/services_data.py
pyhugegraph/structure/vertex_data.py
pyhugegraph/structure/vertex_label_data.py
pyhugegraph/utils/__init__.py
pyhugegraph/utils/constants.py
pyhugegraph/utils/exceptions.py
pyhugegraph/utils/huge_config.py
pyhugegraph/utils/huge_decorator.py
pyhugegraph/utils/huge_requests.py
pyhugegraph/utils/huge_router.py
pyhugegraph/utils/log.py
pyhugegraph/utils/util.py
tests/api/__init__.py
tests/api/test_auth.py
tests/api/test_graph.py
tests/api/test_graphs.py
tests/api/test_gremlin.py
tests/api/test_metric.py
tests/api/test_schema.py
tests/api/test_task.py
tests/api/test_traverser.py
tests/api/test_variable.py
tests/api/test_version.py
hugegraph_python-1.5.0.dist-info/METADATA
hugegraph_python-1.5.0.dist-info/WHEEL
hugegraph_python-1.5.0.dist-info/top_level.txt
hugegraph_python-1.5.0.dist-info/RECORD
