Metadata-Version: 2.2
Name: hugegraph-python
Version: 1.5.0
Summary: A Python SDK for Apache HugeGraph
Home-page: https://github.com/apache/incubator-hugegraph-ai
Author: Apache HugeGraph Contributors
Author-email: dev@hugegraph.apache.org
Classifier: Programming Language :: Python :: 3
Classifier: License :: OSI Approved :: Apache Software License
Classifier: Operating System :: OS Independent
Requires-Python: >=3.9
Requires-Dist: decorator~=5.1.1
Requires-Dist: requests~=2.32.0
Requires-Dist: setuptools~=70.0.0
Requires-Dist: urllib3~=2.2.2
Requires-Dist: rich~=13.9.4
Dynamic: author
Dynamic: author-email
Dynamic: classifier
Dynamic: description
Dynamic: description-content-type
Dynamic: home-page
Dynamic: requires-dist
Dynamic: requires-python
Dynamic: summary
